odoo/addons/l10n_th_gov_purchase_report/README.rst
odoo/addons/l10n_th_gov_purchase_report/__init__.py
odoo/addons/l10n_th_gov_purchase_report/__manifest__.py
odoo/addons/l10n_th_gov_purchase_report/data/report_data.xml
odoo/addons/l10n_th_gov_purchase_report/i18n/l10n_th_gov_purchase_report.pot
odoo/addons/l10n_th_gov_purchase_report/readme/CONTRIBUTORS.rst
odoo/addons/l10n_th_gov_purchase_report/readme/DESCRIPTION.rst
odoo/addons/l10n_th_gov_purchase_report/reports/__init__.py
odoo/addons/l10n_th_gov_purchase_report/reports/common_report_xlsx.py
odoo/addons/l10n_th_gov_purchase_report/reports/non_purchase_report_xlsx.py
odoo/addons/l10n_th_gov_purchase_report/reports/purchase_report_xlsx.py
odoo/addons/l10n_th_gov_purchase_report/reports/purchase_tracking_report_xlsx.py
odoo/addons/l10n_th_gov_purchase_report/security/ir.model.access.csv
odoo/addons/l10n_th_gov_purchase_report/static/description/icon.png
odoo/addons/l10n_th_gov_purchase_report/static/description/index.html
odoo/addons/l10n_th_gov_purchase_report/tests/__init__.py
odoo/addons/l10n_th_gov_purchase_report/tests/test_gov_purchase_report.py
odoo/addons/l10n_th_gov_purchase_report/views/purchase_menu.xml
odoo/addons/l10n_th_gov_purchase_report/wizard/__init__.py
odoo/addons/l10n_th_gov_purchase_report/wizard/common_purchase_wizard.py
odoo/addons/l10n_th_gov_purchase_report/wizard/non_purchase_report_wizard.py
odoo/addons/l10n_th_gov_purchase_report/wizard/non_purchase_report_wizard_view.xml
odoo/addons/l10n_th_gov_purchase_report/wizard/purchase_report_wizard.py
odoo/addons/l10n_th_gov_purchase_report/wizard/purchase_report_wizard_view.xml
odoo/addons/l10n_th_gov_purchase_report/wizard/purchase_tracking_report_wizard.py
odoo/addons/l10n_th_gov_purchase_report/wizard/purchase_tracking_report_wizard.xml
odoo_addon_l10n_th_gov_purchase_report-15.0.1.0.2.dist-info/METADATA
odoo_addon_l10n_th_gov_purchase_report-15.0.1.0.2.dist-info/WHEEL
odoo_addon_l10n_th_gov_purchase_report-15.0.1.0.2.dist-info/top_level.txt
odoo_addon_l10n_th_gov_purchase_report-15.0.1.0.2.dist-info/RECORD
