Metadata-Version: 2.1
Name: odoo-addon-l10n_th_gov_purchase_report
Version: 15.0.1.0.2
Summary: Thai Localization - Government Purchase Report
Home-page: https://github.com/OCA/l10n-thailand
Author: Ecosoft, Odoo Community Association (OCA)
Author-email: support@odoo-community.org
License: AGPL-3
Classifier: Programming Language :: Python
Classifier: Framework :: Odoo
Classifier: Framework :: Odoo :: 15.0
Classifier: License :: OSI Approved :: GNU Affero General Public License v3
Classifier: Development Status :: 3 - Alpha
Requires-Python: >=3.8
Requires-Dist: odoo-addon-date-range<15.1dev,>=15.0dev
Requires-Dist: odoo-addon-hr-expense-sequence<15.1dev,>=15.0dev
Requires-Dist: odoo-addon-l10n-th-account-tax-expense<15.1dev,>=15.0dev
Requires-Dist: odoo-addon-l10n-th-gov-hr-expense<15.1dev,>=15.0dev
Requires-Dist: odoo-addon-l10n-th-gov-purchase-agreement<15.1dev,>=15.0dev
Requires-Dist: odoo-addon-l10n-th-gov-purchase-guarantee<15.1dev,>=15.0dev
Requires-Dist: odoo-addon-l10n-th-gov-purchase-request<15.1dev,>=15.0dev
Requires-Dist: odoo-addon-purchase-invoice-plan<15.1dev,>=15.0dev
Requires-Dist: odoo-addon-purchase-rfq-number<15.1dev,>=15.0dev
Requires-Dist: odoo-addon-purchase-work-acceptance-invoice-plan<15.1dev,>=15.0dev
Requires-Dist: odoo-addon-report-xlsx-helper<15.1dev,>=15.0dev
Requires-Dist: odoo<15.1dev,>=15.0a
